pyimouapi/__init__.py
pyimouapi/const.py
pyimouapi/device.py
pyimouapi/exceptions.py
pyimouapi/ha_device.py
pyimouapi/openapi.py
pyimouapi-1.2.0.dist-info/LICENSE
pyimouapi-1.2.0.dist-info/METADATA
pyimouapi-1.2.0.dist-info/WHEEL
pyimouapi-1.2.0.dist-info/top_level.txt
pyimouapi-1.2.0.dist-info/RECORD
