Metadata-Version: 2.1
Name: pyimouapi
Version: 1.2.0
Summary: A package for imou open api
Home-page: https://github.com/Imou-OpenPlatform/Py-Imou-Open-Api
Author: Imou-OpenPlatform
Author-email: cloud_openteam_service@imou.com
License: MIT
Classifier: Intended Audience :: Developers
Classifier: Operating System :: OS Independent
Classifier: Programming Language :: Python :: 3
Classifier: Topic :: Software Development :: Libraries
License-File: LICENSE
